<annotation>
	<folder>Cars</folder>
	<filename>Cars.21b9263f-4450-11ec-b499-0433c2f55c1c.jpg</filename>
	<path>/home/esteban/git/Deep_Learning_varied/Computer Vision/Challenge/Computer Vision/data/images/Cars/Cars.21b9263f-4450-11ec-b499-0433c2f55c1c.jpg</path>
	<source>
		<database>Unknown</database>
	</source>
	<size>
		<width>1920</width>
		<height>1080</height>
		<depth>3</depth>
	</size>
	<segmented>0</segmented>
	<object>
		<name>Cars</name>
		<pose>Unspecified</pose>
		<truncated>0</truncated>
		<difficult>0</difficult>
		<bndbox>
			<xmin>1164</xmin>
			<ymin>723</ymin>
			<xmax>1426</xmax>
			<ymax>891</ymax>
		</bndbox>
	</object>
	<object>
		<name>Cars</name>
		<pose>Unspecified</pose>
		<truncated>0</truncated>
		<difficult>0</difficult>
		<bndbox>
			<xmin>828</xmin>
			<ymin>652</ymin>
			<xmax>1047</xmax>
			<ymax>818</ymax>
		</bndbox>
	</object>
	<object>
		<name>Cars</name>
		<pose>Unspecified</pose>
		<truncated>0</truncated>
		<difficult>0</difficult>
		<bndbox>
			<xmin>1059</xmin>
			<ymin>545</ymin>
			<xmax>1284</xmax>
			<ymax>706</ymax>
		</bndbox>
	</object>
	<object>
		<name>Cars</name>
		<pose>Unspecified</pose>
		<truncated>0</truncated>
		<difficult>0</difficult>
		<bndbox>
			<xmin>1404</xmin>
			<ymin>382</ymin>
			<xmax>1510</xmax>
			<ymax>460</ymax>
		</bndbox>
	</object>
	<object>
		<name>Cars</name>
		<pose>Unspecified</pose>
		<truncated>0</truncated>
		<difficult>0</difficult>
		<bndbox>
			<xmin>862</xmin>
			<ymin>548</ymin>
			<xmax>1026</xmax>
			<ymax>643</ymax>
		</bndbox>
	</object>
	<object>
		<name>Cars</name>
		<pose>Unspecified</pose>
		<truncated>0</truncated>
		<difficult>0</difficult>
		<bndbox>
			<xmin>914</xmin>
			<ymin>493</ymin>
			<xmax>1033</xmax>
			<ymax>553</ymax>
		</bndbox>
	</object>
	<object>
		<name>Cars</name>
		<pose>Unspecified</pose>
		<truncated>0</truncated>
		<difficult>0</difficult>
		<bndbox>
			<xmin>849</xmin>
			<ymin>403</ymin>
			<xmax>951</xmax>
			<ymax>487</ymax>
		</bndbox>
	</object>
	<object>
		<name>Cars</name>
		<pose>Unspecified</pose>
		<truncated>0</truncated>
		<difficult>0</difficult>
		<bndbox>
			<xmin>896</xmin>
			<ymin>337</ymin>
			<xmax>974</xmax>
			<ymax>422</ymax>
		</bndbox>
	</object>
	<object>
		<name>Cars</name>
		<pose>Unspecified</pose>
		<truncated>0</truncated>
		<difficult>0</difficult>
		<bndbox>
			<xmin>979</xmin>
			<ymin>240</ymin>
			<xmax>1051</xmax>
			<ymax>283</ymax>
		</bndbox>
	</object>
	<object>
		<name>Cars</name>
		<pose>Unspecified</pose>
		<truncated>0</truncated>
		<difficult>0</difficult>
		<bndbox>
			<xmin>485</xmin>
			<ymin>362</ymin>
			<xmax>536</xmax>
			<ymax>425</ymax>
		</bndbox>
	</object>
	<object>
		<name>Cars</name>
		<pose>Unspecified</pose>
		<truncated>0</truncated>
		<difficult>0</difficult>
		<bndbox>
			<xmin>841</xmin>
			<ymin>301</ymin>
			<xmax>926</xmax>
			<ymax>337</ymax>
		</bndbox>
	</object>
	<object>
		<name>Cars</name>
		<pose>Unspecified</pose>
		<truncated>0</truncated>
		<difficult>0</difficult>
		<bndbox>
			<xmin>904</xmin>
			<ymin>262</ymin>
			<xmax>979</xmax>
			<ymax>309</ymax>
		</bndbox>
	</object>
</annotation>
